Dockerfile
LICENSE
MANIFEST.in
README.rst
requirements.txt
setup.py
artman/__init__.py
artman/cli/__init__.py
artman/cli/configure.py
artman/cli/main.py
artman/cli/support.py
artman/config/__init__.py
artman/config/converter.py
artman/config/loader.py
artman/config/proto/__init__.py
artman/config/proto/config_pb2.py
artman/config/proto/user_config_pb2.py
artman/pipelines/__init__.py
artman/pipelines/code_generation.py
artman/pipelines/core_generation.py
artman/pipelines/gapic_generation.py
artman/pipelines/grpc_generation.py
artman/pipelines/pipeline_base.py
artman/pipelines/pipeline_factory.py
artman/pipelines/sample_pipeline.py
artman/tasks/__init__.py
artman/tasks/descriptor_set_tasks.py
artman/tasks/emit_success.py
artman/tasks/format_tasks.py
artman/tasks/gapic_tasks.py
artman/tasks/io_tasks.py
artman/tasks/package_metadata_tasks.py
artman/tasks/protoc_tasks.py
artman/tasks/python_grpc_tasks.py
artman/tasks/sample_tasks.py
artman/tasks/task_base.py
artman/utils/__init__.py
artman/utils/config_util.py
artman/utils/lang_params.py
artman/utils/logger.py
artman/utils/protoc_utils.py
artman/utils/task_utils.py
googleapis_artman.egg-info/PKG-INFO
googleapis_artman.egg-info/SOURCES.txt
googleapis_artman.egg-info/dependency_links.txt
googleapis_artman.egg-info/entry_points.txt
googleapis_artman.egg-info/requires.txt
googleapis_artman.egg-info/top_level.txt
test/smoketest_artman.py
test/test_package_metadata_task.py
test/test_python_package_change_task.py